yggdrasil_mc/__init__.py
yggdrasil_mc/client.py
yggdrasil_mc/exceptions.py
yggdrasil_mc/models.py
yggdrasil_mc/utils.py
yggdrasil_mc-0.2.7.dist-info/LICENSE
yggdrasil_mc-0.2.7.dist-info/METADATA
yggdrasil_mc-0.2.7.dist-info/WHEEL
yggdrasil_mc-0.2.7.dist-info/RECORD
